splineplot/__init__.py
splineplot-0.3.1.dist-info/LICENSE
splineplot-0.3.1.dist-info/METADATA
splineplot-0.3.1.dist-info/WHEEL
splineplot-0.3.1.dist-info/RECORD
