Metadata-Version: 2.1
Name: splineplot
Version: 0.3.1
Summary: 
Home-page: https://github.com/badge/splineplot
License: Apache 2.0
Author: Matthew Badger
Author-email: matt@branchenergy.com
Requires-Python: >=3.10,<4.0
Classifier: License :: Other/Proprietary License
Classifier: Programming Language :: Python :: 3
Classifier: Programming Language :: Python :: 3.10
Classifier: Programming Language :: Python :: 3.11
Requires-Dist: matplotlib (>=3.6.0)
Requires-Dist: pandas (>=1.4.2)
Requires-Dist: statsmodels (>=0.13.2)
Project-URL: Repository, https://github.com/badge/splineplot
